zoom_auto_creator.py
zoom_auto_creator-0.0.4.dist-info/WHEEL
zoom_auto_creator-0.0.4.dist-info/METADATA
zoom_auto_creator-0.0.4.dist-info/RECORD
