Metadata-Version: 2.1
Name: zoom-auto-creator
Version: 0.0.4
Summary: Creating Zoom Rooms
Author: Bohdan Salamakha
Author-email: allen.avanheim@gmail.com
Requires-Python: >=3.10,<4.0
Classifier: Programming Language :: Python :: 3
Classifier: Programming Language :: Python :: 3.10
Requires-Dist: Pillow (>=9.2.0,<10.0.0)
Requires-Dist: pyautogui (>=0.9.53,<0.10.0)
